LICENSE
README.md
setup.py
src/moths/__init__.py
src/moths.egg-info/PKG-INFO
src/moths.egg-info/SOURCES.txt
src/moths.egg-info/dependency_links.txt
src/moths.egg-info/top_level.txt
src/moths/ancientArchi/__init__.py
src/moths/ancientArchi/fashi_db_helper.py
src/moths/misc/__init__.py
src/moths/utility/__init__.py
src/moths/utility/_calculation.py
src/moths/utility/_data_organization.py