Metadata-Version: 2.4
Name: moths
Version: 0.0.6
Summary: 为 grasshopper 参数化设计模组 moths 的支持工具
Home-page: https://coding-x.tech/
Author: Richie Bao-(coding-x.tech)
Author-email: richiebao@outlook.com
License: MIT
Platform: any
Requires-Python: >=3.6
License-File: LICENSE
Dynamic: author
Dynamic: author-email
Dynamic: description
Dynamic: description-content-type
Dynamic: home-page
Dynamic: license
Dynamic: license-file
Dynamic: platform
Dynamic: requires-python
Dynamic: summary
